rule_based_model/RB_model.py
rule_based_model/Rule_based_tester.py
rule_based_model/__init__.py
rule_based_model/first_2word.pkl
rule_based_model/first_3word.pkl
rule_based_model/first_word.pkl
rule_based_model/match_A.pkl
rule_based_model-0.0.5.dist-info/LICENSE
rule_based_model-0.0.5.dist-info/METADATA
rule_based_model-0.0.5.dist-info/WHEEL
rule_based_model-0.0.5.dist-info/top_level.txt
rule_based_model-0.0.5.dist-info/RECORD
